MANIFEST.in
setup.py
django_file_sharing.egg-info/PKG-INFO
django_file_sharing.egg-info/SOURCES.txt
django_file_sharing.egg-info/dependency_links.txt
django_file_sharing.egg-info/not-zip-safe
django_file_sharing.egg-info/top_level.txt
file_sharing/__init__.py
file_sharing/models.py
file_sharing/tests.py
file_sharing/tools.py
file_sharing/urls.py
file_sharing/views.py
file_sharing/media/css/bootstrap-responsive.css
file_sharing/media/css/bootstrap-responsive.min.css
file_sharing/media/css/bootstrap.css
file_sharing/media/css/bootstrap.min.css
file_sharing/media/css/uploader.css
file_sharing/media/css/uploader.css~
file_sharing/media/img/glyphicons-halflings-white.png
file_sharing/media/img/glyphicons-halflings.png
file_sharing/media/js/backbone-min.js
file_sharing/media/js/bootstrap.min.js
file_sharing/media/js/fileuploader.js
file_sharing/media/js/jquery.min.js
file_sharing/media/js/underscore-min.js
file_sharing/media/js/upload.js
file_sharing/migrations/0001_initial.py
file_sharing/migrations/0002_auto__add_userdata.py
file_sharing/migrations/__init__.py
file_sharing/templates/base/file_sharing.html
file_sharing/templates/base/file_sharing.html~
file_sharing/templates/file_sharing/index.html
file_sharing/templatetags/__init__.py
file_sharing/templatetags/__init__.pyc
file_sharing/templatetags/file_tags.py
file_sharing/templatetags/file_tags.pyc