Metadata-Version: 1.1
Name: django-file-sharing
Version: 0.2.1
Summary: file sharing application
Home-page: https://github.com/karoon/django-file-sharing
Author: vahid chakoshy
Author-email: vchakoshy@gmail.com
License: UNKNOWN
Platform: UNKNOWN
Classifier: Framework :: Django
Classifier: Intended Audience :: Developers
Classifier: License :: OSI Approved :: BSD License
Classifier: Operating System :: OS Independent
Classifier: Programming Language :: Python
Classifier: Topic :: Internet :: WWW/HTTP
